[
  {
    "Nome": "1º A Alice Ramalho Souza"
  },
  {
    "Nome": "1º A Ana Julia Borges Souza"
  },
  {
    "Nome": "1º A Arthur Jhonatan Pereira Lima"
  },
  {
    "Nome": "1º A Arthur Mozart Batista Santos"
  },
  {
    "Nome": "1º A Bernardo Dante Café de Azevedo"
  },
  {
    "Nome": "1º A Caio Jardson Dias Lima"
  },
  {
    "Nome": "1º A Carlos Eduardo Santos de Jesus"
  },
  {
    "Nome": "1º A Cristian Rennan Gomes Oliveira dos Santos"
  },
  {
    "Nome": "1º A Davi Lucas Conceição Santos"
  },
  {
    "Nome": "1º A Davi Luiz Torquato Mota"
  },
  {
    "Nome": "1º A Enzo Gabriel Gomes Cavalcante Martins"
  },
  {
    "Nome": "1º A Erick Ruan Pereira dos Santos"
  },
  {
    "Nome": "1º A Izac Maciel Campos Viana"
  },
  {
    "Nome": "1º A João Isaac Barbosa dos Santos"
  },
  {
    "Nome": "1º A João Miguel Silva dos Santos"
  },
  {
    "Nome": "1º A João Paulo Gonçalves da Silva"
  },
  {
    "Nome": "1º A Julia Maynara Menezes Santos"
  },
  {
    "Nome": "1º A Julia Santos Souza"
  },
  {
    "Nome": "1º A Kaio Ruan da Silva Matos"
  },
  {
    "Nome": "1º A Lara Kawanny Lima dos Santos"
  },
  {
    "Nome": "1º A Luna Yara Santos da Conceição"
  },
  {
    "Nome": "1º A Marlon Brito Ferreira Lima"
  },
   {
    "Nome": "1º A Mayconn Nycollas Araújo Gonzaga"
  },
  {
    "Nome": "1º A Pamella Wislayne dos Santos Martins"
  },
  {
    "Nome": "1º A Pedro Otávio Soares Monteiro"
  },
  {
    "Nome": "1º A Pietra Ramalho Santos Sousa"
  },
  {
    "Nome": "1º A Valéria Soares dos Anjos"
  },
  {
    "Nome": "1º A Vitória Santana Silva"
  },
  {
    "Nome": "1º A Yan Carlos de Oliveira"
  },
  {
    "Nome": "1º B Adryan Rafael Santos dos Anjos"
  },
  {
    "Nome": "1º B Adriana Monteiro Rocha"
  },
   {
    "Nome": "1º B Anna Cecília dos Santos Bezerra"
  }, 
  {
    "Nome": "1º B Anny Sophia Vieira Araújo"
  },
  {
    "Nome": "1º B Arthur Melo dos Santos"
  },
  {
    "Nome": "1º B Bejamyn Isack Candido de Oliveira"
  },
  {
    "Nome": "1º B Clara Valentina Satiro Gonçalves"
  },
  {
    "Nome": "1º B Daniel Dantas de Santana"
  },
  {
    "Nome": "1º B Enzo Samuel dos Santos Bispo"
  },  
  {
    "Nome": "1º B Esther Silva Souza dos Santos"
  },
  {
    "Nome": "1º B Evily Vitória Ferre"
  },
  {
    "Nome": "1º B Gabriela Matias dos Santos"
  },
  {
    "Nome": "1º B Guilherme Gentil Santos Junior"
  },
  {
    "Nome": "1º B Ian Lucas de Souza Gomes"
  },
  {
    "Nome": "1º B Jamille Vitória dos Santos"
  }, 
  {
    "Nome": "1º B Ketilin Tawany de Jesus dos Santos"
  },
  {
    "Nome": "1º B Luis Gustavo Silva Santana"
  },
  {
    "Nome": "1º B Marcos Franklin Cavalcante Oliveira"
  },
  {
    "Nome": "1º B Maria Eduarda Muniz Santos"
  },
  {
    "Nome": "1º B Maria Fernanda Conceição Dantas"
  },
  {
    "Nome": "1º B Matheus Gustavo Santos de Jesus"
  },  
  {
    "Nome": "1º B Maycon David Dantas Brito"
  },
  {
    "Nome": "1º B Miguel Rocha Carvalho da Costa"
  },
  {
    "Nome": "1º B Nicholas Davi Santana Mota Nascimento"
  },
  {
    "Nome": "1º B Nicole Leticia de Lima Azevedo"
  },
   {
    "Nome": "1º B Samuel Custódio Amorim ALves"
  }, 
  {
    "Nome": "1º B Samuel Santana Sales"
  }, 
  {
    "Nome": "1º B Sophia Caroliny Ferreira Silva"
  },
  {
    "Nome": "Outro (a)"
  }
]
